allauth_d120_provider/__init__.py
allauth_d120_provider/account_adapter.py
allauth_d120_provider/admin.py
allauth_d120_provider/apps.py
allauth_d120_provider/models.py
allauth_d120_provider/provider.py
allauth_d120_provider/signals.py
allauth_d120_provider/tests.py
allauth_d120_provider/urls.py
allauth_d120_provider/views.py
allauth_d120_provider/migrations/0001_initial.py
allauth_d120_provider/migrations/__init__.py
django_allauth_d120-0.0.8.dist-info/LICENSE
django_allauth_d120-0.0.8.dist-info/METADATA
django_allauth_d120-0.0.8.dist-info/WHEEL
django_allauth_d120-0.0.8.dist-info/top_level.txt
django_allauth_d120-0.0.8.dist-info/RECORD
